sine_table.vh
logic [0:255] [15:0] sine_table = {
16'h0000,
16'h0000,
16'h0324,
16'h0648,
16'h096a,
16'h0c8c,
16'h0fab,
16'h12c8,
16'h15e2,
16'h18f9,
16'h1c0b,
16'h1f1a,
16'h2223,
16'h2528,
16'h2826,
16'h2b1f,
16'h2e11,
16'h30fb,
16'h33df,
16'h36ba,
16'h398c,
16'h3c56,
16'h3f17,
16'h41ce,
16'h447a,
16'h471c,
16'h49b4,
16'h4c3f,
16'h4ebf,
16'h5133,
16'h539b,
16'h55f5,
16'h5842,
16'h5a82,
16'h5cb3,
16'h5ed7,
16'h60eb,
16'h62f1,
16'h64e8,
16'h66cf,
16'h68a6,
16'h6a6d,
16'h6c23,
16'h6dc9,
16'h6f5e,
16'h70e2,
16'h7254,
16'h73b5,
16'h7504,
16'h7641,
16'h776b,
16'h7884,
16'h7989,
16'h7a7c,
16'h7b5c,
16'h7c29,
16'h7ce3,
16'h7d89,
16'h7e1d,
16'h7e9c,
16'h7f09,
16'h7f61,
16'h7fa6,
16'h7fd8,
16'h7ff5,
16'h7fff,
16'h7ff5,
16'h7fd8,
16'h7fa6,
16'h7f61,
16'h7f09,
16'h7e9c,
16'h7e1d,
16'h7d89,
16'h7ce3,
16'h7c29,
16'h7b5c,
16'h7a7c,
16'h7989,
16'h7884,
16'h776b,
16'h7641,
16'h7504,
16'h73b5,
16'h7254,
16'h70e2,
16'h6f5e,
16'h6dc9,
16'h6c23,
16'h6a6d,
16'h68a6,
16'h66cf,
16'h64e8,
16'h62f1,
16'h60eb,
16'h5ed7,
16'h5cb3,
16'h5a82,
16'h5842,
16'h55f5,
16'h539b,
16'h5133,
16'h4ebf,
16'h4c3f,
16'h49b4,
16'h471c,
16'h447a,
16'h41ce,
16'h3f17,
16'h3c56,
16'h398c,
16'h36ba,
16'h33df,
16'h30fb,
16'h2e11,
16'h2b1f,
16'h2826,
16'h2528,
16'h2223,
16'h1f1a,
16'h1c0b,
16'h18f9,
16'h15e2,
16'h12c8,
16'h0fab,
16'h0c8c,
16'h096a,
16'h0648,
16'h0324,
16'h0000,
16'hfcdc,
16'hf9b8,
16'hf696,
16'hf374,
16'hf055,
16'hed38,
16'hea1e,
16'he707,
16'he3f5,
16'he0e6,
16'hdddd,
16'hdad8,
16'hd7da,
16'hd4e1,
16'hd1ef,
16'hcf05,
16'hcc21,
16'hc946,
16'hc674,
16'hc3aa,
16'hc0e9,
16'hbe32,
16'hbb86,
16'hb8e4,
16'hb64c,
16'hb3c1,
16'hb141,
16'haecd,
16'hac65,
16'haa0b,
16'ha7be,
16'ha57e,
16'ha34d,
16'ha129,
16'h9f15,
16'h9d0f,
16'h9b18,
16'h9931,
16'h975a,
16'h9593,
16'h93dd,
16'h9237,
16'h90a2,
16'h8f1e,
16'h8dac,
16'h8c4b,
16'h8afc,
16'h89bf,
16'h8895,
16'h877c,
16'h8677,
16'h8584,
16'h84a4,
16'h83d7,
16'h831d,
16'h8277,
16'h81e3,
16'h8164,
16'h80f7,
16'h809f,
16'h805a,
16'h8028,
16'h800b,
16'h8001,
16'h800b,
16'h8028,
16'h805a,
16'h809f,
16'h80f7,
16'h8164,
16'h81e3,
16'h8277,
16'h831d,
16'h83d7,
16'h84a4,
16'h8584,
16'h8677,
16'h877c,
16'h8895,
16'h89bf,
16'h8afc,
16'h8c4b,
16'h8dac,
16'h8f1e,
16'h90a2,
16'h9237,
16'h93dd,
16'h9593,
16'h975a,
16'h9931,
16'h9b18,
16'h9d0f,
16'h9f15,
16'ha129,
16'ha34d,
16'ha57e,
16'ha7be,
16'haa0b,
16'hac65,
16'haecd,
16'hb141,
16'hb3c1,
16'hb64c,
16'hb8e4,
16'hbb86,
16'hbe32,
16'hc0e9,
16'hc3aa,
16'hc674,
16'hc946,
16'hcc21,
16'hcf05,
16'hd1ef,
16'hd4e1,
16'hd7da,
16'hdad8,
16'hdddd,
16'he0e6,
16'he3f5,
16'he707,
16'hea1e,
16'hed38,
16'hf055,
16'hf374,
16'hf696
};

count.v
`timescale 1ns/10ps

module counter_8bit (
        input wire  rst,
        input wire  clk,
        output [15:0] sine_out
);
        reg [7:0] tcount;
        `include "sine_table.vh"

        assign sine_out = sine_table[tcount];
        always @(posedge clk or posedge rst) begin
                if(rst) begin
                        tcount <= 0;
                end
                else begin
                        tcount <= tcount + 1;
                end
        end

endmodule

`define PEROID 10
module counter_8bit_tb ;
        reg clk;
        reg rst;
        wire [7:0] counter;
        wire [15:0] sine_out;

        counter_8bit dut (
                .rst(rst),
                .clk(clk),
                .sine_out(sine_out)
        );
/*
        include "sine_table.vh"
        function [15:0] sinef;
                input[7:0] angle;
                begin
                        sinef = $sin(2 * angle * $acos(-1)/256)*($pow(2,15)-1);
                        $display("%4h", sinef);
                end
        endfunction

        assign sine_out = sine_table[counter];
*/
        initial begin
                 $dumpfile("wave.vcd");
                 $dumpvars (0, counter_8bit_tb);
                 clk = 0;
                 forever #(`PEROID/2) clk = ~clk;
        end
        initial begin
                rst = 1;
                #50;
                rst = 0;
                #10000;
                $finish();
        end
endmodule

wave.vcd
$date
	Wed Feb 19 22:11:42 2025
$end
$version
	Icarus Verilog
$end
$timescale
	10ps
$end
$scope module counter_8bit_tb $end
$var wire 16 ! sine_out [15:0] $end
$var reg 1 " clk $end
$var reg 1 # rst $end
$scope module dut $end
$var wire 1 " clk $end
$var wire 1 # rst $end
$var wire 16 $ sine_out [15:0] $end
$var reg 4096 % sine_table [4095:0] $end
$var reg 8 & tcount [7:0] $end
$upscope $end
$upscope $end
$enddefinitions $end
#0
$dumpvars
b0 &
b1100100100000001100100100000001001011010100000110010001100000011111010101100010010110010000001010111100010000110001111100100011100000010110001111100011010001000100010001100100101001010000010100000100110001010110001111100101110000100010011000011111011001100111101111100110110101110100011100110001100001111000101011000111111000101110100000111001110010001000111101001000111000111000100100110110100010011000011111101001110101111110101000100110011010100111001101101010101111101010101100001000010010110101000001001011100101100110101111011010111011000001110101101100010111100010110010011101000011001101100111101101000101001100110101001101101011011000010001101101101110010010110111101011110011100001110001001110010010101000111001110110101011101010000010001110110010000010111011101101011011110001000010001111001100010010111101001111100011110110101110001111100001010010111110011100011011111011000100101111110000111010111111010011100011111110000100101111111011000010111111110100110011111111101100001111111111101010111111111111111011111111111010101111111110110000111111110100110011111110110000101111111000010010111111010011100011111100001110101111101100010010111110011100011011111000010100101111011010111000111101001111100011110011000100101111000100001000111011101101011011101100100000101110101000001000111001110110101011100100101010001110000111000100110111101011110011011011100100101101100001000110110101001101101011010001010011001100110110011110110010011101000011000101111000101100000111010110101111011010111010111001011001101011010100000100101100001000010010101011111010101010011100110110101000100110011010011101011111101001100001111110100100110110100010001110001110001000100011110100100000111001110001111110001011100111100010101100011100110001100001101101011101000110011110111110011000011111011001011100001000100101011000111110010100000100110001001010010100000100010001000110001111100011010000111000000101100011000111110010001010111100010000100101100100000001111101010110000110010001100000010010110101000000110010010000000001100100100000000000000000011111100110111001111100110111000111101101001011011110011011101001111000001010101111011010011100011101010000111101110011100000111111000111111010111100000111001101101110111011101110110101101100011010111110110101101010011100001110100011110111111001111000001011100110000100001110010010100011011000110011101001100001110101010110000001110100110111110001100101011101110000110101110001110010010110110010011001011001111000001101100010100000110101110110011011010110001100101101010100000101110100111101111101010010101111110101000110100110110100001001010011001111100010101100111010000111110011011000110001001100100110001100101110101101010010101100100111001001111011101100100100011011110010000101000101000111100011110100011011010110010001100010010111000101011111100100010011011111110001000100101011000011101111100100001100111011110000101100001001000010010100100100000111101011110000011000111011000001001110111100000011110001110000001011001001000000011110111100000001001111110000000010110101000000000101000100000000000101110000000000000011000000000001011100000000010100010000000010110101000000010011111100000001111011110000001011001001000000111100011100000100111011110000011000111011000001111010111100001001010010010000101100001001000011001110111100001110111110010001000100101011000100110111111100010101111110010001100010010111000110110101100100011110001111010010000101000101001001000110111100100111101110110010101100100111001011101011010100110010011000110011011000110001001110100001111100111110001010110100001001010011010001101001101101001010111111010100111101111101010101000001011101011000110010110101110110011011011000101000001101100111100000110110110010011001011100011100100101110111000011010111110001100101100000011101001110000111010101011000110011101001100100101000110110011000010000111001111000001011101000111101111110101001110000111010111110110101101101011011000110111011101110111100000111001101110001111110101111001110000011111101010000111101110110100111000111100000101010111110011011101001111011010010110 %
b0 $
1#
0"
b0 !
$end
#500
1"
#1000
0"
#1500
1"
#2000
0"
#2500
1"
#3000
0"
#3500
1"
#4000
0"
#4500
1"
#5000
0"
0#
#5500
b1 &
1"
#6000
0"
#6500
b10 &
1"
#7000
0"
#7500
b1100100100 !
b1100100100 $
b11 &
1"
#8000
0"
#8500
b11001001000 !
b11001001000 $
b100 &
1"
#9000
0"
#9500
b100101101010 !
b100101101010 $
b101 &
1"
#10000
0"
#10500
b110010001100 !
b110010001100 $
b110 &
1"
#11000
0"
#11500
b111110101011 !
b111110101011 $
b111 &
1"
#12000
0"
#12500
b1001011001000 !
b1001011001000 $
b1000 &
1"
#13000
0"
#13500
b1010111100010 !
b1010111100010 $
b1001 &
1"
#14000
0"
#14500
b1100011111001 !
b1100011111001 $
b1010 &
1"
#15000
0"
#15500
b1110000001011 !
b1110000001011 $
b1011 &
1"
#16000
0"
#16500
b1111100011010 !
b1111100011010 $
b1100 &
1"
#17000
0"
#17500
b10001000100011 !
b10001000100011 $
b1101 &
1"
#18000
0"
#18500
b10010100101000 !
b10010100101000 $
b1110 &
1"
#19000
0"
#19500
b10100000100110 !
b10100000100110 $
b1111 &
1"
#20000
0"
#20500
b10101100011111 !
b10101100011111 $
b10000 &
1"
#21000
0"
#21500
b10111000010001 !
b10111000010001 $
b10001 &
1"
#22000
0"
#22500
b11000011111011 !
b11000011111011 $
b10010 &
1"
#23000
0"
#23500
b11001111011111 !
b11001111011111 $
b10011 &
1"
#24000
0"
#24500
b11011010111010 !
b11011010111010 $
b10100 &
1"
#25000
0"
#25500
b11100110001100 !
b11100110001100 $
b10101 &
1"
#26000
0"
#26500
b11110001010110 !
b11110001010110 $
b10110 &
1"
#27000
0"
#27500
b11111100010111 !
b11111100010111 $
b10111 &
1"
#28000
0"
#28500
b100000111001110 !
b100000111001110 $
b11000 &
1"
#29000
0"
#29500
b100010001111010 !
b100010001111010 $
b11001 &
1"
#30000
0"
#30500
b100011100011100 !
b100011100011100 $
b11010 &
1"
#31000
0"
#31500
b100100110110100 !
b100100110110100 $
b11011 &
1"
#32000
0"
#32500
b100110000111111 !
b100110000111111 $
b11100 &
1"
#33000
0"
#33500
b100111010111111 !
b100111010111111 $
b11101 &
1"
#34000
0"
#34500
b101000100110011 !
b101000100110011 $
b11110 &
1"
#35000
0"
#35500
b101001110011011 !
b101001110011011 $
b11111 &
1"
#36000
0"
#36500
b101010111110101 !
b101010111110101 $
b100000 &
1"
#37000
0"
#37500
b101100001000010 !
b101100001000010 $
b100001 &
1"
#38000
0"
#38500
b101101010000010 !
b101101010000010 $
b100010 &
1"
#39000
0"
#39500
b101110010110011 !
b101110010110011 $
b100011 &
1"
#40000
0"
#40500
b101111011010111 !
b101111011010111 $
b100100 &
1"
#41000
0"
#41500
b110000011101011 !
b110000011101011 $
b100101 &
1"
#42000
0"
#42500
b110001011110001 !
b110001011110001 $
b100110 &
1"
#43000
0"
#43500
b110010011101000 !
b110010011101000 $
b100111 &
1"
#44000
0"
#44500
b110011011001111 !
b110011011001111 $
b101000 &
1"
#45000
0"
#45500
b110100010100110 !
b110100010100110 $
b101001 &
1"
#46000
0"
#46500
b110101001101101 !
b110101001101101 $
b101010 &
1"
#47000
0"
#47500
b110110000100011 !
b110110000100011 $
b101011 &
1"
#48000
0"
#48500
b110110111001001 !
b110110111001001 $
b101100 &
1"
#49000
0"
#49500
b110111101011110 !
b110111101011110 $
b101101 &
1"
#50000
0"
#50500
b111000011100010 !
b111000011100010 $
b101110 &
1"
#51000
0"
#51500
b111001001010100 !
b111001001010100 $
b101111 &
1"
#52000
0"
#52500
b111001110110101 !
b111001110110101 $
b110000 &
1"
#53000
0"
#53500
b111010100000100 !
b111010100000100 $
b110001 &
1"
#54000
0"
#54500
b111011001000001 !
b111011001000001 $
b110010 &
1"
#55000
0"
#55500
b111011101101011 !
b111011101101011 $
b110011 &
1"
#56000
0"
#56500
b111100010000100 !
b111100010000100 $
b110100 &
1"
#57000
0"
#57500
b111100110001001 !
b111100110001001 $
b110101 &
1"
#58000
0"
#58500
b111101001111100 !
b111101001111100 $
b110110 &
1"
#59000
0"
#59500
b111101101011100 !
b111101101011100 $
b110111 &
1"
#60000
0"
#60500
b111110000101001 !
b111110000101001 $
b111000 &
1"
#61000
0"
#61500
b111110011100011 !
b111110011100011 $
b111001 &
1"
#62000
0"
#62500
b111110110001001 !
b111110110001001 $
b111010 &
1"
#63000
0"
#63500
b111111000011101 !
b111111000011101 $
b111011 &
1"
#64000
0"
#64500
b111111010011100 !
b111111010011100 $
b111100 &
1"
#65000
0"
#65500
b111111100001001 !
b111111100001001 $
b111101 &
1"
#66000
0"
#66500
b111111101100001 !
b111111101100001 $
b111110 &
1"
#67000
0"
#67500
b111111110100110 !
b111111110100110 $
b111111 &
1"
#68000
0"
#68500
b111111111011000 !
b111111111011000 $
b1000000 &
1"
#69000
0"
#69500
b111111111110101 !
b111111111110101 $
b1000001 &
1"
#70000
0"
#70500
b111111111111111 !
b111111111111111 $
b1000010 &
1"
#71000
0"
#71500
b111111111110101 !
b111111111110101 $
b1000011 &
1"
#72000
0"
#72500
b111111111011000 !
b111111111011000 $
b1000100 &
1"
#73000
0"
#73500
b111111110100110 !
b111111110100110 $
b1000101 &
1"
#74000
0"
#74500
b111111101100001 !
b111111101100001 $
b1000110 &
1"
#75000
0"
#75500
b111111100001001 !
b111111100001001 $
b1000111 &
1"
#76000
0"
#76500
b111111010011100 !
b111111010011100 $
b1001000 &
1"
#77000
0"
#77500
b111111000011101 !
b111111000011101 $
b1001001 &
1"
#78000
0"
#78500
b111110110001001 !
b111110110001001 $
b1001010 &
1"
#79000
0"
#79500
b111110011100011 !
b111110011100011 $
b1001011 &
1"
#80000
0"
#80500
b111110000101001 !
b111110000101001 $
b1001100 &
1"
#81000
0"
#81500
b111101101011100 !
b111101101011100 $
b1001101 &
1"
#82000
0"
#82500
b111101001111100 !
b111101001111100 $
b1001110 &
1"
#83000
0"
#83500
b111100110001001 !
b111100110001001 $
b1001111 &
1"
#84000
0"
#84500
b111100010000100 !
b111100010000100 $
b1010000 &
1"
#85000
0"
#85500
b111011101101011 !
b111011101101011 $
b1010001 &
1"
#86000
0"
#86500
b111011001000001 !
b111011001000001 $
b1010010 &
1"
#87000
0"
#87500
b111010100000100 !
b111010100000100 $
b1010011 &
1"
#88000
0"
#88500
b111001110110101 !
b111001110110101 $
b1010100 &
1"
#89000
0"
#89500
b111001001010100 !
b111001001010100 $
b1010101 &
1"
#90000
0"
#90500
b111000011100010 !
b111000011100010 $
b1010110 &
1"
#91000
0"
#91500
b110111101011110 !
b110111101011110 $
b1010111 &
1"
#92000
0"
#92500
b110110111001001 !
b110110111001001 $
b1011000 &
1"
#93000
0"
#93500
b110110000100011 !
b110110000100011 $
b1011001 &
1"
#94000
0"
#94500
b110101001101101 !
b110101001101101 $
b1011010 &
1"
#95000
0"
#95500
b110100010100110 !
b110100010100110 $
b1011011 &
1"
#96000
0"
#96500
b110011011001111 !
b110011011001111 $
b1011100 &
1"
#97000
0"
#97500
b110010011101000 !
b110010011101000 $
b1011101 &
1"
#98000
0"
#98500
b110001011110001 !
b110001011110001 $
b1011110 &
1"
#99000
0"
#99500
b110000011101011 !
b110000011101011 $
b1011111 &
1"
#100000
0"
#100500
b101111011010111 !
b101111011010111 $
b1100000 &
1"
#101000
0"
#101500
b101110010110011 !
b101110010110011 $
b1100001 &
1"
#102000
0"
#102500
b101101010000010 !
b101101010000010 $
b1100010 &
1"
#103000
0"
#103500
b101100001000010 !
b101100001000010 $
b1100011 &
1"
#104000
0"
#104500
b101010111110101 !
b101010111110101 $
b1100100 &
1"
#105000
0"
#105500
b101001110011011 !
b101001110011011 $
b1100101 &
1"
#106000
0"
#106500
b101000100110011 !
b101000100110011 $
b1100110 &
1"
#107000
0"
#107500
b100111010111111 !
b100111010111111 $
b1100111 &
1"
#108000
0"
#108500
b100110000111111 !
b100110000111111 $
b1101000 &
1"
#109000
0"
#109500
b100100110110100 !
b100100110110100 $
b1101001 &
1"
#110000
0"
#110500
b100011100011100 !
b100011100011100 $
b1101010 &
1"
#111000
0"
#111500
b100010001111010 !
b100010001111010 $
b1101011 &
1"
#112000
0"
#112500
b100000111001110 !
b100000111001110 $
b1101100 &
1"
#113000
0"
#113500
b11111100010111 !
b11111100010111 $
b1101101 &
1"
#114000
0"
#114500
b11110001010110 !
b11110001010110 $
b1101110 &
1"
#115000
0"
#115500
b11100110001100 !
b11100110001100 $
b1101111 &
1"
#116000
0"
#116500
b11011010111010 !
b11011010111010 $
b1110000 &
1"
#117000
0"
#117500
b11001111011111 !
b11001111011111 $
b1110001 &
1"
#118000
0"
#118500
b11000011111011 !
b11000011111011 $
b1110010 &
1"
#119000
0"
#119500
b10111000010001 !
b10111000010001 $
b1110011 &
1"
#120000
0"
#120500
b10101100011111 !
b10101100011111 $
b1110100 &
1"
#121000
0"
#121500
b10100000100110 !
b10100000100110 $
b1110101 &
1"
#122000
0"
#122500
b10010100101000 !
b10010100101000 $
b1110110 &
1"
#123000
0"
#123500
b10001000100011 !
b10001000100011 $
b1110111 &
1"
#124000
0"
#124500
b1111100011010 !
b1111100011010 $
b1111000 &
1"
#125000
0"
#125500
b1110000001011 !
b1110000001011 $
b1111001 &
1"
#126000
0"
#126500
b1100011111001 !
b1100011111001 $
b1111010 &
1"
#127000
0"
#127500
b1010111100010 !
b1010111100010 $
b1111011 &
1"
#128000
0"
#128500
b1001011001000 !
b1001011001000 $
b1111100 &
1"
#129000
0"
#129500
b111110101011 !
b111110101011 $
b1111101 &
1"
#130000
0"
#130500
b110010001100 !
b110010001100 $
b1111110 &
1"
#131000
0"
#131500
b100101101010 !
b100101101010 $
b1111111 &
1"
#132000
0"
#132500
b11001001000 !
b11001001000 $
b10000000 &
1"
#133000
0"
#133500
b1100100100 !
b1100100100 $
b10000001 &
1"
#134000
0"
#134500
b0 !
b0 $
b10000010 &
1"
#135000
0"
#135500
b1111110011011100 !
b1111110011011100 $
b10000011 &
1"
#136000
0"
#136500
b1111100110111000 !
b1111100110111000 $
b10000100 &
1"
#137000
0"
#137500
b1111011010010110 !
b1111011010010110 $
b10000101 &
1"
#138000
0"
#138500
b1111001101110100 !
b1111001101110100 $
b10000110 &
1"
#139000
0"
#139500
b1111000001010101 !
b1111000001010101 $
b10000111 &
1"
#140000
0"
#140500
b1110110100111000 !
b1110110100111000 $
b10001000 &
1"
#141000
0"
#141500
b1110101000011110 !
b1110101000011110 $
b10001001 &
1"
#142000
0"
#142500
b1110011100000111 !
b1110011100000111 $
b10001010 &
1"
#143000
0"
#143500
b1110001111110101 !
b1110001111110101 $
b10001011 &
1"
#144000
0"
#144500
b1110000011100110 !
b1110000011100110 $
b10001100 &
1"
#145000
0"
#145500
b1101110111011101 !
b1101110111011101 $
b10001101 &
1"
#146000
0"
#146500
b1101101011011000 !
b1101101011011000 $
b10001110 &
1"
#147000
0"
#147500
b1101011111011010 !
b1101011111011010 $
b10001111 &
1"
#148000
0"
#148500
b1101010011100001 !
b1101010011100001 $
b10010000 &
1"
#149000
0"
#149500
b1101000111101111 !
b1101000111101111 $
b10010001 &
1"
#150000
0"
#150500
b1100111100000101 !
b1100111100000101 $
b10010010 &
1"
#151000
0"
#151500
b1100110000100001 !
b1100110000100001 $
b10010011 &
1"
#152000
0"
#152500
b1100100101000110 !
b1100100101000110 $
b10010100 &
1"
#153000
0"
#153500
b1100011001110100 !
b1100011001110100 $
b10010101 &
1"
#154000
0"
#154500
b1100001110101010 !
b1100001110101010 $
b10010110 &
1"
#155000
0"
#155500
b1100000011101001 !
b1100000011101001 $
b10010111 &
1"
#156000
0"
#156500
b1011111000110010 !
b1011111000110010 $
b10011000 &
1"
#157000
0"
#157500
b1011101110000110 !
b1011101110000110 $
b10011001 &
1"
#158000
0"
#158500
b1011100011100100 !
b1011100011100100 $
b10011010 &
1"
#159000
0"
#159500
b1011011001001100 !
b1011011001001100 $
b10011011 &
1"
#160000
0"
#160500
b1011001111000001 !
b1011001111000001 $
b10011100 &
1"
#161000
0"
#161500
b1011000101000001 !
b1011000101000001 $
b10011101 &
1"
#162000
0"
#162500
b1010111011001101 !
b1010111011001101 $
b10011110 &
1"
#163000
0"
#163500
b1010110001100101 !
b1010110001100101 $
b10011111 &
1"
#164000
0"
#164500
b1010101000001011 !
b1010101000001011 $
b10100000 &
1"
#165000
0"
#165500
b1010011110111110 !
b1010011110111110 $
b10100001 &
1"
#166000
0"
#166500
b1010010101111110 !
b1010010101111110 $
b10100010 &
1"
#167000
0"
#167500
b1010001101001101 !
b1010001101001101 $
b10100011 &
1"
#168000
0"
#168500
b1010000100101001 !
b1010000100101001 $
b10100100 &
1"
#169000
0"
#169500
b1001111100010101 !
b1001111100010101 $
b10100101 &
1"
#170000
0"
#170500
b1001110100001111 !
b1001110100001111 $
b10100110 &
1"
#171000
0"
#171500
b1001101100011000 !
b1001101100011000 $
b10100111 &
1"
#172000
0"
#172500
b1001100100110001 !
b1001100100110001 $
b10101000 &
1"
#173000
0"
#173500
b1001011101011010 !
b1001011101011010 $
b10101001 &
1"
#174000
0"
#174500
b1001010110010011 !
b1001010110010011 $
b10101010 &
1"
#175000
0"
#175500
b1001001111011101 !
b1001001111011101 $
b10101011 &
1"
#176000
0"
#176500
b1001001000110111 !
b1001001000110111 $
b10101100 &
1"
#177000
0"
#177500
b1001000010100010 !
b1001000010100010 $
b10101101 &
1"
#178000
0"
#178500
b1000111100011110 !
b1000111100011110 $
b10101110 &
1"
#179000
0"
#179500
b1000110110101100 !
b1000110110101100 $
b10101111 &
1"
#180000
0"
#180500
b1000110001001011 !
b1000110001001011 $
b10110000 &
1"
#181000
0"
#181500
b1000101011111100 !
b1000101011111100 $
b10110001 &
1"
#182000
0"
#182500
b1000100110111111 !
b1000100110111111 $
b10110010 &
1"
#183000
0"
#183500
b1000100010010101 !
b1000100010010101 $
b10110011 &
1"
#184000
0"
#184500
b1000011101111100 !
b1000011101111100 $
b10110100 &
1"
#185000
0"
#185500
b1000011001110111 !
b1000011001110111 $
b10110101 &
1"
#186000
0"
#186500
b1000010110000100 !
b1000010110000100 $
b10110110 &
1"
#187000
0"
#187500
b1000010010100100 !
b1000010010100100 $
b10110111 &
1"
#188000
0"
#188500
b1000001111010111 !
b1000001111010111 $
b10111000 &
1"
#189000
0"
#189500
b1000001100011101 !
b1000001100011101 $
b10111001 &
1"
#190000
0"
#190500
b1000001001110111 !
b1000001001110111 $
b10111010 &
1"
#191000
0"
#191500
b1000000111100011 !
b1000000111100011 $
b10111011 &
1"
#192000
0"
#192500
b1000000101100100 !
b1000000101100100 $
b10111100 &
1"
#193000
0"
#193500
b1000000011110111 !
b1000000011110111 $
b10111101 &
1"
#194000
0"
#194500
b1000000010011111 !
b1000000010011111 $
b10111110 &
1"
#195000
0"
#195500
b1000000001011010 !
b1000000001011010 $
b10111111 &
1"
#196000
0"
#196500
b1000000000101000 !
b1000000000101000 $
b11000000 &
1"
#197000
0"
#197500
b1000000000001011 !
b1000000000001011 $
b11000001 &
1"
#198000
0"
#198500
b1000000000000001 !
b1000000000000001 $
b11000010 &
1"
#199000
0"
#199500
b1000000000001011 !
b1000000000001011 $
b11000011 &
1"
#200000
0"
#200500
b1000000000101000 !
b1000000000101000 $
b11000100 &
1"
#201000
0"
#201500
b1000000001011010 !
b1000000001011010 $
b11000101 &
1"
#202000
0"
#202500
b1000000010011111 !
b1000000010011111 $
b11000110 &
1"
#203000
0"
#203500
b1000000011110111 !
b1000000011110111 $
b11000111 &
1"
#204000
0"
#204500
b1000000101100100 !
b1000000101100100 $
b11001000 &
1"
#205000
0"
#205500
b1000000111100011 !
b1000000111100011 $
b11001001 &
1"
#206000
0"
#206500
b1000001001110111 !
b1000001001110111 $
b11001010 &
1"
#207000
0"
#207500
b1000001100011101 !
b1000001100011101 $
b11001011 &
1"
#208000
0"
#208500
b1000001111010111 !
b1000001111010111 $
b11001100 &
1"
#209000
0"
#209500
b1000010010100100 !
b1000010010100100 $
b11001101 &
1"
#210000
0"
#210500
b1000010110000100 !
b1000010110000100 $
b11001110 &
1"
#211000
0"
#211500
b1000011001110111 !
b1000011001110111 $
b11001111 &
1"
#212000
0"
#212500
b1000011101111100 !
b1000011101111100 $
b11010000 &
1"
#213000
0"
#213500
b1000100010010101 !
b1000100010010101 $
b11010001 &
1"
#214000
0"
#214500
b1000100110111111 !
b1000100110111111 $
b11010010 &
1"
#215000
0"
#215500
b1000101011111100 !
b1000101011111100 $
b11010011 &
1"
#216000
0"
#216500
b1000110001001011 !
b1000110001001011 $
b11010100 &
1"
#217000
0"
#217500
b1000110110101100 !
b1000110110101100 $
b11010101 &
1"
#218000
0"
#218500
b1000111100011110 !
b1000111100011110 $
b11010110 &
1"
#219000
0"
#219500
b1001000010100010 !
b1001000010100010 $
b11010111 &
1"
#220000
0"
#220500
b1001001000110111 !
b1001001000110111 $
b11011000 &
1"
#221000
0"
#221500
b1001001111011101 !
b1001001111011101 $
b11011001 &
1"
#222000
0"
#222500
b1001010110010011 !
b1001010110010011 $
b11011010 &
1"
#223000
0"
#223500
b1001011101011010 !
b1001011101011010 $
b11011011 &
1"
#224000
0"
#224500
b1001100100110001 !
b1001100100110001 $
b11011100 &
1"
#225000
0"
#225500
b1001101100011000 !
b1001101100011000 $
b11011101 &
1"
#226000
0"
#226500
b1001110100001111 !
b1001110100001111 $
b11011110 &
1"
#227000
0"
#227500
b1001111100010101 !
b1001111100010101 $
b11011111 &
1"
#228000
0"
#228500
b1010000100101001 !
b1010000100101001 $
b11100000 &
1"
#229000
0"
#229500
b1010001101001101 !
b1010001101001101 $
b11100001 &
1"
#230000
0"
#230500
b1010010101111110 !
b1010010101111110 $
b11100010 &
1"
#231000
0"
#231500
b1010011110111110 !
b1010011110111110 $
b11100011 &
1"
#232000
0"
#232500
b1010101000001011 !
b1010101000001011 $
b11100100 &
1"
#233000
0"
#233500
b1010110001100101 !
b1010110001100101 $
b11100101 &
1"
#234000
0"
#234500
b1010111011001101 !
b1010111011001101 $
b11100110 &
1"
#235000
0"
#235500
b1011000101000001 !
b1011000101000001 $
b11100111 &
1"
#236000
0"
#236500
b1011001111000001 !
b1011001111000001 $
b11101000 &
1"
#237000
0"
#237500
b1011011001001100 !
b1011011001001100 $
b11101001 &
1"
#238000
0"
#238500
b1011100011100100 !
b1011100011100100 $
b11101010 &
1"
#239000
0"
#239500
b1011101110000110 !
b1011101110000110 $
b11101011 &
1"
#240000
0"
#240500
b1011111000110010 !
b1011111000110010 $
b11101100 &
1"
#241000
0"
#241500
b1100000011101001 !
b1100000011101001 $
b11101101 &
1"
#242000
0"
#242500
b1100001110101010 !
b1100001110101010 $
b11101110 &
1"
#243000
0"
#243500
b1100011001110100 !
b1100011001110100 $
b11101111 &
1"
#244000
0"
#244500
b1100100101000110 !
b1100100101000110 $
b11110000 &
1"
#245000
0"
#245500
b1100110000100001 !
b1100110000100001 $
b11110001 &
1"
#246000
0"
#246500
b1100111100000101 !
b1100111100000101 $
b11110010 &
1"
#247000
0"
#247500
b1101000111101111 !
b1101000111101111 $
b11110011 &
1"
#248000
0"
#248500
b1101010011100001 !
b1101010011100001 $
b11110100 &
1"
#249000
0"
#249500
b1101011111011010 !
b1101011111011010 $
b11110101 &
1"
#250000
0"
#250500
b1101101011011000 !
b1101101011011000 $
b11110110 &
1"
#251000
0"
#251500
b1101110111011101 !
b1101110111011101 $
b11110111 &
1"
#252000
0"
#252500
b1110000011100110 !
b1110000011100110 $
b11111000 &
1"
#253000
0"
#253500
b1110001111110101 !
b1110001111110101 $
b11111001 &
1"
#254000
0"
#254500
b1110011100000111 !
b1110011100000111 $
b11111010 &
1"
#255000
0"
#255500
b1110101000011110 !
b1110101000011110 $
b11111011 &
1"
#256000
0"
#256500
b1110110100111000 !
b1110110100111000 $
b11111100 &
1"
#257000
0"
#257500
b1111000001010101 !
b1111000001010101 $
b11111101 &
1"
#258000
0"
#258500
b1111001101110100 !
b1111001101110100 $
b11111110 &
1"
#259000
0"
#259500
b1111011010010110 !
b1111011010010110 $
b11111111 &
1"
#260000
0"
#260500
b0 !
b0 $
b0 &
1"
#261000
0"
#261500
b1 &
1"
#262000
0"
#262500
b10 &
1"
#263000
0"
#263500
b1100100100 !
b1100100100 $
b11 &
1"
#264000
0"
#264500
b11001001000 !
b11001001000 $
b100 &
1"
#265000
0"
#265500
b100101101010 !
b100101101010 $
b101 &
1"
#266000
0"
#266500
b110010001100 !
b110010001100 $
b110 &
1"
#267000
0"
#267500
b111110101011 !
b111110101011 $
b111 &
1"
#268000
0"
#268500
b1001011001000 !
b1001011001000 $
b1000 &
1"
#269000
0"
#269500
b1010111100010 !
b1010111100010 $
b1001 &
1"
#270000
0"
#270500
b1100011111001 !
b1100011111001 $
b1010 &
1"
#271000
0"
#271500
b1110000001011 !
b1110000001011 $
b1011 &
1"
#272000
0"
#272500
b1111100011010 !
b1111100011010 $
b1100 &
1"
#273000
0"
#273500
b10001000100011 !
b10001000100011 $
b1101 &
1"
#274000
0"
#274500
b10010100101000 !
b10010100101000 $
b1110 &
1"
#275000
0"
#275500
b10100000100110 !
b10100000100110 $
b1111 &
1"
#276000
0"
#276500
b10101100011111 !
b10101100011111 $
b10000 &
1"
#277000
0"
#277500
b10111000010001 !
b10111000010001 $
b10001 &
1"
#278000
0"
#278500
b11000011111011 !
b11000011111011 $
b10010 &
1"
#279000
0"
